hiddify_reality_scanner/VERSION
hiddify_reality_scanner/__init__.py
hiddify_reality_scanner/__main__.py
hiddify_reality_scanner/base.py
hiddify_reality_scanner/cli.py
hiddify_reality_scanner/templates/xray.json.j2
hiddify_reality_scanner-1.8.0.dist-info/LICENSE
hiddify_reality_scanner-1.8.0.dist-info/METADATA
hiddify_reality_scanner-1.8.0.dist-info/WHEEL
hiddify_reality_scanner-1.8.0.dist-info/entry_points.txt
hiddify_reality_scanner-1.8.0.dist-info/top_level.txt
hiddify_reality_scanner-1.8.0.dist-info/RECORD
