Metadata-Version: 2.1
Name: hiddify-reality-scanner
Version: 1.8.0
Summary: Awesome hiddify_reality_scanner created by hiddify
Home-page: https://github.com/hiddify/Hiddify_Reality_Scanner/
Author: hiddify
License-File: LICENSE
Requires-Dist: httpx
Requires-Dist: httpx-socks[asyncio]
Requires-Dist: requests
Requires-Dist: jinja2
Requires-Dist: tqdm
Provides-Extra: test
Requires-Dist: pytest ; extra == 'test'
Requires-Dist: coverage ; extra == 'test'
Requires-Dist: flake8 ; extra == 'test'
Requires-Dist: black ; extra == 'test'
Requires-Dist: isort ; extra == 'test'
Requires-Dist: pytest-cov ; extra == 'test'
Requires-Dist: mypy ; extra == 'test'
Requires-Dist: gitchangelog ; extra == 'test'
Requires-Dist: mkdocs ; extra == 'test'
